<mdb:MD_Metadata xmlns:xsi="http://www.w3.org/2001/XMLSchema-instance" xmlns:cit="http://standards.iso.org/iso/19115/-3/cit/1.0" xmlns:gex="http://standards.iso.org/iso/19115/-3/gex/1.0" xmlns:lan="http://standards.iso.org/iso/19115/-3/lan/1.0" xmlns:mcc="http://standards.iso.org/iso/19115/-3/mcc/1.0" xmlns:mco="http://standards.iso.org/iso/19115/-3/mco/1.0" xmlns:mdb="http://standards.iso.org/iso/19115/-3/mdb/1.0" xmlns:mds="http://standards.iso.org/iso/19115/-3/mds/1.0" xmlns:mri="http://standards.iso.org/iso/19115/-3/mri/1.0" xmlns:gco="http://standards.iso.org/iso/19115/-3/gco/1.0" xmlns:gml="http://www.opengis.net/gml/3.2" xmlns:xlink="http://www.w3.org/1999/xlink" xsi:schemaLocation="http://standards.iso.org/iso/19115/-3/mdb/1.0 http://standards.iso.org/iso/19115/-3/mdb/1.0/mdb.xsd">
    <mdb:metadataIdentifier>
        <mcc:MD_Identifier> 
            <mcc:code>
                <gco:CharacterString>edu.ucar.opensky::articles:18433</gco:CharacterString>
            </mcc:code>
        </mcc:MD_Identifier>
    </mdb:metadataIdentifier>
    <mdb:defaultLocale>
        <lan:PT_Locale>
            <lan:language>
                <lan:LanguageCode codeList="codeListLocation#LanguageCode" codeListValue="eng; USA">eng; USA</lan:LanguageCode>
            </lan:language>
            <lan:characterEncoding>
                <lan:MD_CharacterSetCode codeList="codeListLocation#MD_CharacterSetCode" codeListValue="utf8">utf8</lan:MD_CharacterSetCode>
            </lan:characterEncoding>
        </lan:PT_Locale>
    </mdb:defaultLocale>
    <mdb:metadataScope>
        <mdb:MD_MetadataScope>
            <mdb:resourceScope>
                <mcc:MD_ScopeCode codeList="codeListLocation#MD_ScopeCode" codeListValue="document">document</mcc:MD_ScopeCode>
            </mdb:resourceScope>
        </mdb:MD_MetadataScope>
    </mdb:metadataScope>
    <mdb:contact><cit:CI_Responsibility>
    <cit:role>
        <cit:CI_RoleCode codeList="codeListLocation#CI_RoleCode" codeListValue="pointOfContact">pointOfContact
        </cit:CI_RoleCode>
    </cit:role>
    <cit:party>
        <cit:CI_Organisation>
            <cit:name>
                <gco:CharacterString>UCAR/NCAR - Library</gco:CharacterString>
            </cit:name>
            <cit:contactInfo>
                <cit:CI_Contact>
                    <cit:address>
                        <cit:CI_Address>
                            <cit:deliveryPoint>
                                <gco:CharacterString>PO Box 3000</gco:CharacterString>
                            </cit:deliveryPoint>
                            <cit:city>
                                <gco:CharacterString>Boulder</gco:CharacterString>
                            </cit:city>
                            <cit:administrativeArea>
                                <gco:CharacterString>CO</gco:CharacterString>
                            </cit:administrativeArea>
                            <cit:postalCode>
                                <gco:CharacterString>80307-3000</gco:CharacterString>
                            </cit:postalCode>
                            <cit:electronicMailAddress>
                                <gco:CharacterString>opensky@ucar.edu</gco:CharacterString>
                            </cit:electronicMailAddress>
                        </cit:CI_Address>
                    </cit:address>
                    <cit:onlineResource>
                        <cit:CI_OnlineResource>
                            <cit:linkage>
                                <gco:CharacterString>http://opensky.ucar.edu/</gco:CharacterString>
                            </cit:linkage>
                            <cit:name>
                                <gco:CharacterString>homepage</gco:CharacterString>
                            </cit:name>
                        </cit:CI_OnlineResource>
                    </cit:onlineResource>
                </cit:CI_Contact>
            </cit:contactInfo>
            <cit:individual>
                <cit:CI_Individual>
                    <cit:positionName>
                        <gco:CharacterString>OpenSky Support</gco:CharacterString>
                    </cit:positionName>
                </cit:CI_Individual>
            </cit:individual>
        </cit:CI_Organisation>
    </cit:party>
</cit:CI_Responsibility></mdb:contact>
    <mdb:dateInfo>
        <cit:CI_Date>
            <cit:date>
                <gco:DateTime>2017-10-25T21:27:24.891839</gco:DateTime>
            </cit:date>
            <cit:dateType>
                <cit:CI_DateTypeCode codeList="codeListLocation#CI_DateTypeCode" codeListValue="creation">creation</cit:CI_DateTypeCode>
            </cit:dateType>
        </cit:CI_Date>
    </mdb:dateInfo>
    <mdb:metadataStandard>
        <cit:CI_Citation>
            <cit:title>
                <gco:CharacterString>ISO 19115-2 Geographic Information - Metadata - Part 2:
                    Extensions for Imagery and Gridded Data</gco:CharacterString>
            </cit:title>
            <cit:edition>
                <gco:CharacterString>ISO 19115-2:2009(E)</gco:CharacterString>
            </cit:edition>
        </cit:CI_Citation>
    </mdb:metadataStandard>
    <mdb:identificationInfo>
        <mri:MD_DataIdentification>
            <mri:citation>
                <cit:CI_Citation>
                    <cit:title>
                        <gco:CharacterString>Optimization of an enclosed gas analyzer sampling system for measuring eddy covariance fluxes of H&#8322;O and CO&#8322;</gco:CharacterString>
                    </cit:title>
                    <cit:date>
                        <cit:CI_Date>
                            <cit:date>
                                <gco:DateTime>2016-03-31T00:00:00Z</gco:DateTime>
                            </cit:date>
                            <cit:dateType>
                                <cit:CI_DateTypeCode codeList="codeListLocation#CI_DateTypeCode" codeListValue="publication">publication</cit:CI_DateTypeCode>
                            </cit:dateType>
                        </cit:CI_Date>
                    </cit:date>

                    <cit:identifier>
                        <mcc:MD_Identifier>
                            <mcc:code>
                                <gco:CharacterString>http://n2t.net/ark:/85065/d72z174g</gco:CharacterString>
                            </mcc:code>
                        </mcc:MD_Identifier>
                    </cit:identifier>

                    <cit:identifier>
                        <mcc:MD_Identifier>
                            <mcc:code>
                                <gco:CharacterString>doi:10.5194/amt-9-1341-2016</gco:CharacterString>
                            </mcc:code>
                        </mcc:MD_Identifier>
                    </cit:identifier>

                    <cit:identifier>
                        <mcc:MD_Identifier>
                            <mcc:code>
                                <gco:CharacterString>ark:/85065/d72z174g</gco:CharacterString>
                            </mcc:code>
                        </mcc:MD_Identifier>
                    </cit:identifier>

                    <cit:citedResponsibleParty>
                        <cit:CI_Responsibility>
                            <cit:role>
                                <cit:CI_RoleCode codeList="codeListLocation#CI_RoleCode" codeListValue="author">author</cit:CI_RoleCode>
                            </cit:role>
                            <cit:party>
                                <cit:CI_Individual>
                                    <cit:name>
                                        <gco:CharacterString>Metzger, Stefan</gco:CharacterString>
                                    </cit:name>
                                </cit:CI_Individual>
                            </cit:party>
                        </cit:CI_Responsibility>
                    </cit:citedResponsibleParty>
                    
                    <cit:citedResponsibleParty>
                        <cit:CI_Responsibility>
                            <cit:role>
                                <cit:CI_RoleCode codeList="codeListLocation#CI_RoleCode" codeListValue="author">author</cit:CI_RoleCode>
                            </cit:role>
                            <cit:party>
                                <cit:CI_Individual>
                                    <cit:name>
                                        <gco:CharacterString>Burba, George</gco:CharacterString>
                                    </cit:name>
                                </cit:CI_Individual>
                            </cit:party>
                        </cit:CI_Responsibility>
                    </cit:citedResponsibleParty>
                    
                    <cit:citedResponsibleParty>
                        <cit:CI_Responsibility>
                            <cit:role>
                                <cit:CI_RoleCode codeList="codeListLocation#CI_RoleCode" codeListValue="author">author</cit:CI_RoleCode>
                            </cit:role>
                            <cit:party>
                                <cit:CI_Individual>
                                    <cit:name>
                                        <gco:CharacterString>Burns, Sean</gco:CharacterString>
                                    </cit:name>
                                </cit:CI_Individual>
                            </cit:party>
                        </cit:CI_Responsibility>
                    </cit:citedResponsibleParty>
                    
                    <cit:citedResponsibleParty>
                        <cit:CI_Responsibility>
                            <cit:role>
                                <cit:CI_RoleCode codeList="codeListLocation#CI_RoleCode" codeListValue="author">author</cit:CI_RoleCode>
                            </cit:role>
                            <cit:party>
                                <cit:CI_Individual>
                                    <cit:name>
                                        <gco:CharacterString>Blanken, Peter</gco:CharacterString>
                                    </cit:name>
                                </cit:CI_Individual>
                            </cit:party>
                        </cit:CI_Responsibility>
                    </cit:citedResponsibleParty>
                    
                    <cit:citedResponsibleParty>
                        <cit:CI_Responsibility>
                            <cit:role>
                                <cit:CI_RoleCode codeList="codeListLocation#CI_RoleCode" codeListValue="author">author</cit:CI_RoleCode>
                            </cit:role>
                            <cit:party>
                                <cit:CI_Individual>
                                    <cit:name>
                                        <gco:CharacterString>Li, Jiahong</gco:CharacterString>
                                    </cit:name>
                                </cit:CI_Individual>
                            </cit:party>
                        </cit:CI_Responsibility>
                    </cit:citedResponsibleParty>
                    
                    <cit:citedResponsibleParty>
                        <cit:CI_Responsibility>
                            <cit:role>
                                <cit:CI_RoleCode codeList="codeListLocation#CI_RoleCode" codeListValue="author">author</cit:CI_RoleCode>
                            </cit:role>
                            <cit:party>
                                <cit:CI_Individual>
                                    <cit:name>
                                        <gco:CharacterString>Luo, Hongyan</gco:CharacterString>
                                    </cit:name>
                                </cit:CI_Individual>
                            </cit:party>
                        </cit:CI_Responsibility>
                    </cit:citedResponsibleParty>
                    
                    <cit:citedResponsibleParty>
                        <cit:CI_Responsibility>
                            <cit:role>
                                <cit:CI_RoleCode codeList="codeListLocation#CI_RoleCode" codeListValue="author">author</cit:CI_RoleCode>
                            </cit:role>
                            <cit:party>
                                <cit:CI_Individual>
                                    <cit:name>
                                        <gco:CharacterString>Zulueta, Romel</gco:CharacterString>
                                    </cit:name>
                                </cit:CI_Individual>
                            </cit:party>
                        </cit:CI_Responsibility>
                    </cit:citedResponsibleParty>
                    
                    <cit:citedResponsibleParty>
    <cit:CI_Responsibility>
        <cit:role>
            <cit:CI_RoleCode codeList="codeListLocation#CI_RoleCode" codeListValue="publisher">publisher</cit:CI_RoleCode>
        </cit:role>
        <cit:party>
            <cit:CI_Organisation>
                <cit:name>
                    <gco:CharacterString>UCAR/NCAR - Library</gco:CharacterString>
                </cit:name>
            </cit:CI_Organisation>
        </cit:party>
    </cit:CI_Responsibility>
</cit:citedResponsibleParty><cit:onlineResource>
                        <cit:CI_OnlineResource>
                            <cit:linkage>
                                <gco:CharacterString>http://n2t.net/ark:/85065/d72z174g</gco:CharacterString>
                            </cit:linkage>
                            <cit:name>
                                <gco:CharacterString>Resource Landing Page</gco:CharacterString>
                            </cit:name>
                        </cit:CI_OnlineResource>
                    </cit:onlineResource>


                    <cit:onlineResource>
                        <cit:CI_OnlineResource>
                            <cit:linkage>
                                <gco:CharacterString>https://doi.org/10.5194/amt-9-1341-2016</gco:CharacterString>
                            </cit:linkage>
                            <cit:name>
                                <gco:CharacterString>Resource Full Text</gco:CharacterString>
                            </cit:name>
                        </cit:CI_OnlineResource>
                    </cit:onlineResource>

                </cit:CI_Citation>
            </mri:citation>
            <mri:abstract>
                <gco:CharacterString><![CDATA[Several initiatives are currently emerging to observe the exchange of energy and matter between the earth's surface and atmosphere standardized over larger space and time domains. For example, the National Ecological Observatory Network (NEON) and the Integrated Carbon Observing System (ICOS) are set to provide the ability of unbiased ecological inference across ecoclimatic zones and decades by deploying highly scalable and robust instruments and data processing. In the construction of these observatories, enclosed infrared gas analyzers are widely employed for eddy covariance applications. While these sensors represent a substantial improvement compared to their open- and closed-path predecessors, remaining high-frequency attenuation varies with site properties and gas sampling systems, and requires correction. Here, we show that components of the gas sampling system can substantially contribute to such high-frequency attenuation, but their effects can be significantly reduced by careful system design. From laboratory tests we determine the frequency at which signal attenuation reaches 50&#8239;% for individual parts of the gas sampling system. For different models of rain caps and particulate filters, this frequency falls into ranges of 2.5-16.5&#8239;Hz for CO&#8322;, 2.4-14.3&#8239;Hz for H&#8322;O, and 8.3-21.8&#8239;Hz for CO&#8322;, 1.4-19.9&#8239;Hz for H2O, respectively. A short and thin stainless steel intake tube was found to not limit frequency response, with 50&#8239;% attenuation occurring at frequencies well above 10&#8239;Hz for both H&#8322;O and CO&#8322;. From field tests we found that heating the intake tube and particulate filter continuously with 4&#8239;W was effective, and reduced the occurrence of problematic relative humidity levels (RH&#8239;&#8201;&gt;&#8201;60&#8239;%) by 50&#8239;% in the infrared gas analyzer cell. No further improvement of H&#8322;O frequency response was found for heating in excess of 4&#8239;W. These laboratory and field tests were reconciled using resistor-capacitor theory, and NEON's final gas sampling system was developed on this basis. The design consists of the stainless steel intake tube, a pleated mesh particulate filter and a low-volume rain cap in combination with 4&#8239;W of heating and insulation. In comparison to the original design, this reduced the high-frequency attenuation for H&#8322;O by &#8201;&#8776;&#8201;3&#8725;4, and the remaining cospectral correction did not exceed 3&#8239;%, even at high relative humidity (95&#8239;%). The standardized design can be used across a wide range of ecoclimates and site layouts, and maximizes practicability due to minimal flow resistance and maintenance needs. Furthermore, due to minimal high-frequency spectral loss, it supports the routine application of adaptive correction procedures, and enables largely automated data processing across sites.]]></gco:CharacterString>
            </mri:abstract>
            <mri:pointOfContact><cit:CI_Responsibility>
    <cit:role>
        <cit:CI_RoleCode codeList="codeListLocation#CI_RoleCode" codeListValue="pointOfContact">pointOfContact
        </cit:CI_RoleCode>
    </cit:role>
    <cit:party>
        <cit:CI_Organisation>
            <cit:name>
                <gco:CharacterString>UCAR/NCAR - Library</gco:CharacterString>
            </cit:name>
            <cit:contactInfo>
                <cit:CI_Contact>
                    <cit:address>
                        <cit:CI_Address>
                            <cit:deliveryPoint>
                                <gco:CharacterString>PO Box 3000</gco:CharacterString>
                            </cit:deliveryPoint>
                            <cit:city>
                                <gco:CharacterString>Boulder</gco:CharacterString>
                            </cit:city>
                            <cit:administrativeArea>
                                <gco:CharacterString>CO</gco:CharacterString>
                            </cit:administrativeArea>
                            <cit:postalCode>
                                <gco:CharacterString>80307-3000</gco:CharacterString>
                            </cit:postalCode>
                            <cit:electronicMailAddress>
                                <gco:CharacterString>opensky@ucar.edu</gco:CharacterString>
                            </cit:electronicMailAddress>
                        </cit:CI_Address>
                    </cit:address>
                    <cit:onlineResource>
                        <cit:CI_OnlineResource>
                            <cit:linkage>
                                <gco:CharacterString>http://opensky.ucar.edu/</gco:CharacterString>
                            </cit:linkage>
                            <cit:name>
                                <gco:CharacterString>homepage</gco:CharacterString>
                            </cit:name>
                        </cit:CI_OnlineResource>
                    </cit:onlineResource>
                </cit:CI_Contact>
            </cit:contactInfo>
            <cit:individual>
                <cit:CI_Individual>
                    <cit:positionName>
                        <gco:CharacterString>OpenSky Support</gco:CharacterString>
                    </cit:positionName>
                </cit:CI_Individual>
            </cit:individual>
        </cit:CI_Organisation>
    </cit:party>
</cit:CI_Responsibility></mri:pointOfContact>
            <mri:topicCategory>
                <mri:MD_TopicCategoryCode>geoscientificInformation</mri:MD_TopicCategoryCode>
            </mri:topicCategory>

            <mri:descriptiveKeywords>
                <mri:MD_Keywords>
                    <mri:keyword>
                        <gco:CharacterString>Text</gco:CharacterString>
                    </mri:keyword>
                    <mri:type>
                        <mri:MD_KeywordTypeCode codeList="codeListLocation#MD_KeywordTypeCode" codeListValue="theme">theme</mri:MD_KeywordTypeCode>
                    </mri:type>
                    <mri:thesaurusName>
                        <cit:CI_Citation>
                            <cit:title>
                                <gco:CharacterString>Resource Type</gco:CharacterString>
                            </cit:title>

                            <cit:date>
                                <cit:CI_Date>
                                    <cit:date>
                                        <!--<gco:Date>2016</gco:Date>-->
                                        <gco:DateTime>2016-01-01T00:00:00Z</gco:DateTime>
                                    </cit:date>
                                    <cit:dateType>
                                        <cit:CI_DateTypeCode codeList="codeListLocation#CI_DateTypeCode" codeListValue="publication">publication</cit:CI_DateTypeCode>
                                    </cit:dateType>
                                </cit:CI_Date>
                            </cit:date>
                        </cit:CI_Citation>
                    </mri:thesaurusName>
                </mri:MD_Keywords>
            </mri:descriptiveKeywords>

            <mri:resourceConstraints>
                <mco:MD_LegalConstraints>
                    <mco:useLimitation>
                        <gco:CharacterString>Copyright Author(s) 2016. This work is distributed under the Creative Commons Attribution 3.0 License</gco:CharacterString>
                    </mco:useLimitation>
                    <mco:otherConstraints>
                        <gco:CharacterString>None</gco:CharacterString>
                    </mco:otherConstraints>
                </mco:MD_LegalConstraints>
            </mri:resourceConstraints>

            <mri:defaultLocale>
                <lan:PT_Locale>
                    <lan:language>
                        <lan:LanguageCode codeList="codeListLocation#LanguageCode" codeListValue="eng">eng</lan:LanguageCode>
                    </lan:language>
                    <lan:characterEncoding gco:nilReason="unknown"/>
                </lan:PT_Locale>
            </mri:defaultLocale>
        </mri:MD_DataIdentification>
    </mdb:identificationInfo>

</mdb:MD_Metadata>
